MANIFEST.in
setup.py
example/__init__.py
example/example.py
zygote/__init__.py
zygote/_httpserver.py
zygote/_httpserver_2.py
zygote/accounting.py
zygote/handlers.py
zygote/main.py
zygote/master.py
zygote/message.py
zygote/util.py
zygote/worker.py
zygote.egg-info/PKG-INFO
zygote.egg-info/SOURCES.txt
zygote.egg-info/dependency_links.txt
zygote.egg-info/entry_points.txt
zygote.egg-info/requires.txt
zygote.egg-info/top_level.txt
zygote/resources/__init__.py
zygote/resources/static/__init__.py
zygote/resources/static/base.css
zygote/resources/static/favicon.ico
zygote/resources/static/main.js
zygote/resources/static/mustache.js
zygote/resources/static/reset-min.css
zygote/resources/static/template.html
zygote/resources/templates/__init__.py
zygote/resources/templates/home.html