Metadata-Version: 1.0
Name: zygote
Version: 0.5.3
Summary: A tornado HTTP worker management tool
Home-page: UNKNOWN
Author: Evan Klitzke
Author-email: evan@eklitzke.org
License: Apache License 2.0
Platform: UNKNOWN
